simplejwt_extensions/__init__.py
simplejwt_extensions/authentication.py
simplejwt_extensions/settings.py
simplejwt_extensions-0.2.5.dist-info/LICENSE
simplejwt_extensions-0.2.5.dist-info/WHEEL
simplejwt_extensions-0.2.5.dist-info/METADATA
simplejwt_extensions-0.2.5.dist-info/RECORD
