Metadata-Version: 2.1
Name: simplejwt-extensions
Version: 0.2.5
Summary: 
Home-page: https://github.com/MetLifeLegalPlans/simplejwt-extensions
Author: Bequest, Inc.
Author-email: oss@willing.com
Requires-Python: >=3.6
Classifier: Programming Language :: Python :: 3
Classifier: Programming Language :: Python :: 3.6
Classifier: Programming Language :: Python :: 3.7
Classifier: Programming Language :: Python :: 3.8
Classifier: Programming Language :: Python :: 3.9
Requires-Dist: djangorestframework-simplejwt (>=4.4.0)
Project-URL: Repository, https://github.com/MetLifeLegalPlans/simplejwt-extensions
